terratorch/__about__.py
terratorch/__init__.py
terratorch/__main__.py
terratorch/cli_tools.py
terratorch/utils.py
terratorch/validate_config.py
terratorch/datamodules/__init__.py
terratorch/datamodules/biomassters.py
terratorch/datamodules/burn_intensity.py
terratorch/datamodules/carbonflux.py
terratorch/datamodules/eccc.py
terratorch/datamodules/era5.py
terratorch/datamodules/fire_scars.py
terratorch/datamodules/forestnet.py
terratorch/datamodules/generic_multimodal_data_module.py
terratorch/datamodules/generic_pixel_wise_data_module.py
terratorch/datamodules/generic_scalar_label_data_module.py
terratorch/datamodules/geobench_data_module.py
terratorch/datamodules/geobench_v2_data_module.py
terratorch/datamodules/helio.py
terratorch/datamodules/landslide4sense.py
terratorch/datamodules/m_SA_crop_type.py
terratorch/datamodules/m_VHR10.py
terratorch/datamodules/m_bigearthnet.py
terratorch/datamodules/m_brick_kiln.py
terratorch/datamodules/m_cashew_plantation.py
terratorch/datamodules/m_chesapeake_landcover.py
terratorch/datamodules/m_eurosat.py
terratorch/datamodules/m_forestnet.py
terratorch/datamodules/m_neontree.py
terratorch/datamodules/m_nz_cattle.py
terratorch/datamodules/m_pv4ger.py
terratorch/datamodules/m_pv4ger_seg.py
terratorch/datamodules/m_so2sat.py
terratorch/datamodules/merra2_downscale.py
terratorch/datamodules/multi_temporal_crop_classification.py
terratorch/datamodules/od_aed_elephant.py
terratorch/datamodules/open_sentinel_map.py
terratorch/datamodules/openearthmap.py
terratorch/datamodules/pastis.py
terratorch/datamodules/random.py
terratorch/datamodules/sen1floods11.py
terratorch/datamodules/sen4agrinet.py
terratorch/datamodules/sen4map.py
terratorch/datamodules/substation.py
terratorch/datamodules/torchgeo_data_module.py
terratorch/datamodules/utils.py
terratorch/datasets/__init__.py
terratorch/datasets/biomassters.py
terratorch/datasets/burn_intensity.py
terratorch/datasets/carbonflux.py
terratorch/datasets/fire_scars.py
terratorch-1.2.1.dist-info/licenses/LICENSE
terratorch-1.2.1.dist-info/METADATA
terratorch-1.2.1.dist-info/WHEEL
terratorch-1.2.1.dist-info/entry_points.txt
terratorch-1.2.1.dist-info/top_level.txt
terratorch-1.2.1.dist-info/RECORD
