Metadata-Version: 2.4
Name: terratorch
Version: 1.2.1
Summary: TerraTorch - The geospatial foundation model fine-tuning toolkit
Author: Carlos Gomes, Joao Lucas de Sousa Almeida, Romeo Kienzler, Benedikt Blumenstiel, Francesc Martí Escofet, Paolo Fraccaro, Pedro Henrique Conrado, Jaione Tirapu Azpiroz, Daniela Szwarcman, Bianca Zadrozny, Þorsteinn Elí Gíslason, Raunak Bhansali, Takao Moriyama, Þorsteinn Elí Gíslason
Author-email: terratorch@ibm.com
License: Apache License, Version 2.0
Project-URL: Documentation, https://terrastackai.github.io/terratorch/
Project-URL: Issues, https://github.com/terrastackai/terratorch/issues
Project-URL: Source, https://github.com/terrastackai/terratorch
Keywords: fine-tuning,geospatial foundation models,artificial intelligence
Classifier: Programming Language :: Python :: 3.11
Classifier: Programming Language :: Python :: 3.12
Classifier: Programming Language :: Python :: 3.13
Requires-Python: >=3.10
License-File: LICENSE
Requires-Dist: torch>2.0
Requires-Dist: numpy>=2.2
Requires-Dist: torchvision
Requires-Dist: rioxarray
Requires-Dist: albumentations
Requires-Dist: albucore
Requires-Dist: rasterio
Requires-Dist: torchmetrics
Requires-Dist: geopandas
Requires-Dist: lightly==1.5.22
Requires-Dist: h5py
Requires-Dist: lightning>=2.6.0
Requires-Dist: segmentation-models-pytorch
Requires-Dist: jsonargparse>=4.40.0
Requires-Dist: torchgeo
Requires-Dist: einops
Requires-Dist: timm>=1.0.15
Requires-Dist: pycocotools
Requires-Dist: huggingface_hub
Requires-Dist: tifffile
Requires-Dist: python-box
Requires-Dist: tqdm
Requires-Dist: wandb
Requires-Dist: tensorboard
Requires-Dist: diffusers
Requires-Dist: scikit-learn>=1.3.2
Requires-Dist: scikit-image
Provides-Extra: dev
Requires-Dist: black; extra == "dev"
Requires-Dist: mkdocs-material; extra == "dev"
Requires-Dist: mkdocstrings[python]; extra == "dev"
Requires-Dist: mike; extra == "dev"
Requires-Dist: mkdocs-git-revision-date-localized-plugin; extra == "dev"
Requires-Dist: pre-commit; extra == "dev"
Provides-Extra: test
Requires-Dist: pytest; extra == "test"
Requires-Dist: pytest-coverage; extra == "test"
Requires-Dist: coverage-badge; extra == "test"
Requires-Dist: peft>=0.15.0; extra == "test"
Requires-Dist: diffusers<=0.34.0; extra == "test"
Requires-Dist: tokenizers; extra == "test"
Requires-Dist: dask; extra == "test"
Requires-Dist: wandb; extra == "test"
Requires-Dist: pytest-sugar; extra == "test"
Requires-Dist: numba; extra == "test"
Requires-Dist: hdf5plugin; extra == "test"
Requires-Dist: h5netcdf; extra == "test"
Requires-Dist: geobenchv2==0.9; extra == "test"
Provides-Extra: surya
Requires-Dist: numba; extra == "surya"
Requires-Dist: hdf5plugin; extra == "surya"
Requires-Dist: h5netcdf; extra == "surya"
Requires-Dist: terratorch-surya==0.1.0; extra == "surya"
Provides-Extra: mmseg
Requires-Dist: mmcv; extra == "mmseg"
Requires-Dist: ftfy; extra == "mmseg"
Requires-Dist: regex; extra == "mmseg"
Requires-Dist: openmim; extra == "mmseg"
Provides-Extra: wxc
Requires-Dist: PrithviWxC; extra == "wxc"
Requires-Dist: granitewxc; extra == "wxc"
Provides-Extra: visualize
Requires-Dist: torchview; extra == "visualize"
Requires-Dist: graphviz; extra == "visualize"
Provides-Extra: peft
Requires-Dist: peft>=0.15.0; extra == "peft"
Provides-Extra: geobenchv2
Requires-Dist: geobenchv2==0.9; extra == "geobenchv2"
Requires-Dist: mlflow; extra == "geobenchv2"
Provides-Extra: vllm
Requires-Dist: geobenchv2==0.9; extra == "vllm"
Requires-Dist: vllm>=0.12; extra == "vllm"
Provides-Extra: vllm-test
Requires-Dist: pillow; extra == "vllm-test"
Requires-Dist: imagehash; extra == "vllm-test"
Dynamic: license-file
